README.txt
setup.py
wc/__init__.py
wc.textpage.egg-info/PKG-INFO
wc.textpage.egg-info/SOURCES.txt
wc.textpage.egg-info/dependency_links.txt
wc.textpage.egg-info/namespace_packages.txt
wc.textpage.egg-info/not-zip-safe
wc.textpage.egg-info/top_level.txt
wc/textpage/__init__.py
wc/textpage/browser.py
wc/textpage/configure.zcml
wc/textpage/dublincore.py
wc/textpage/icon.gif
wc/textpage/interfaces.py
wc/textpage/page.py
wc/textpage/tests.py
wc/textpage/view.pt
wc/textpage/wc.textpage-configure.zcml
