Metadata-Version: 1.0
Name: wc.textpage
Version: 2.0.1
Summary: Simple text-base page
Home-page: http://worldcookery.com/Downloads
Author: Philipp von Weitershausen
Author-email: philipp@weitershausen.de
License: UNKNOWN
Platform: UNKNOWN
Classifier: Development Status :: 5 - Production/Stable
Classifier: Framework :: Zope3
Classifier: Intended Audience :: Developers
